adios2/__init__.py
adios2/adios.py
adios2/attribute.py
adios2/derived_variable.py
adios2/engine.py
adios2/file_reader.py
adios2/io.py
adios2/libadios2_atl.so
adios2/libadios2_atl.so.2.11
adios2/libadios2_atl.so.2.11.0
adios2/libadios2_c.so
adios2/libadios2_c.so.2.11
adios2/libadios2_c.so.2.11.0
adios2/libadios2_core.so
adios2/libadios2_core.so.2.11
adios2/libadios2_core.so.2.11.0
adios2/libadios2_cxx.so
adios2/libadios2_cxx.so.2.11
adios2/libadios2_cxx.so.2.11.0
adios2/libadios2_dill.so
adios2/libadios2_dill.so.2.11
adios2/libadios2_dill.so.2.11.0
adios2/libadios2_enet.so
adios2/libadios2_enet.so.2.11
adios2/libadios2_enet.so.2.11.0
adios2/libadios2_evpath.so
adios2/libadios2_evpath.so.2.11
adios2/libadios2_evpath.so.2.11.0
adios2/libadios2_ffs.so
adios2/libadios2_ffs.so.2.11
adios2/libadios2_ffs.so.2.11.0
adios2/libadios2_perfstubs.so
adios2/libadios2_perfstubs.so.2.11
adios2/libadios2_perfstubs.so.2.11.0
adios2/operator.py
adios2/stream.py
adios2/variable.py
adios2/adios2-evpath-modules-2_11/libadios2_cmenet.so
adios2/adios2-evpath-modules-2_11/libadios2_cmepoll.so
adios2/adios2-evpath-modules-2_11/libadios2_cmmulticast.so
adios2/adios2-evpath-modules-2_11/libadios2_cmselect.so
adios2/adios2-evpath-modules-2_11/libadios2_cmsockets.so
adios2/adios2-evpath-modules-2_11/libadios2_cmudp.so
adios2/bindings/__init__.py
adios2/bindings/adios2_bindings.cpython-311-x86_64-linux-gnu.so
adios2/cmake/adios2/CMakeFindDependencyMacro.cmake
adios2/cmake/adios2/FindBZip2.cmake
adios2/cmake/adios2/FindCaliper.cmake
adios2/cmake/adios2/FindCrayDRC.cmake
adios2/cmake/adios2/FindDAOS.cmake
adios2/cmake/adios2/FindDataSpaces.cmake
adios2/cmake/adios2/FindHDF5.cmake
adios2/cmake/adios2/FindIME.cmake
adios2/cmake/adios2/FindLIBFABRIC.cmake
adios2/cmake/adios2/FindMPI.cmake
adios2/cmake/adios2/FindPkgConfig.cmake
adios2/cmake/adios2/FindPython.cmake
adios2/cmake/adios2/FindPythonModule.cmake
adios2/cmake/adios2/FindSZ.cmake
adios2-2.11.0.1012.dist-info/METADATA
adios2-2.11.0.1012.dist-info/WHEEL
adios2-2.11.0.1012.dist-info/RECORD
adios2-2.11.0.1012.dist-info/licenses/LICENSE
