Metadata-Version: 2.2
Name: adios2
Version: 2.11.0.1012
Summary: The Adaptable Input Output System version 2
Keywords: Python,Web,Application,Framework
Author-Email: Caitlin Ross <caitlin.ross@kitware.com>, Chuck Atkins <chuck.atkins@kitware.com>, "Greg S. Eisenhauer" <eisen@cc.gatech.edu>, Junmin Gu <jgu@lbl.gov>, Norbert Podhorszki <pnorbert@ornl.gov>, "Ruonan (Jason) Wang" <wangr1@ornl.gov>, Scott Wittenburg <scott.wittenburg@kitware.com>, Spiros Tsalikis <spiros.tsalikis@kitware.com>, "V. A. Bolea Sanchez" <vicente.bolea@kitware.com>, "William F. Godoy" <godoywf@ornl.gov>
Classifier: Programming Language :: C++
Classifier: License :: OSI Approved :: Apache Software License
Classifier: Operating System :: OS Independent
Project-URL: Homepage, https://github.com/ornladios/adios2
Project-URL: Documentation, https://adios2.readthedocs.io/
Project-URL: Bug Tracker, https://github.com/ornladios/adios2/issues
Project-URL: Discussions, https://github.com/ornladios/ADIOS2/discussions
Project-URL: Changelog, https://github.com/ornladios/ADIOS2/releases
Requires-Python: >=3.8
Requires-Dist: numpy>=1.22
Provides-Extra: dev
Requires-Dist: black; extra == "dev"
Requires-Dist: pip>=21.3; extra == "dev"
